{"name":"surf_fuckyou","lightmapUrl":"https://raw.githubusercontent.com/RSCSurf/SurfMaps3/main/maps/surf_fuckyou/lightmap.json?v=2048-eef4","leafPages":[{"first":0,"count":5971,"url":"https://raw.githubusercontent.com/RSCSurf/SurfMaps3/main/maps/surf_fuckyou/geom/leafpage0.json?v=2048-eef4"}],"dispPages":[{"first":0,"count":0,"url":"https://raw.githubusercontent.com/RSCSurf/SurfMaps3/main/maps/surf_fuckyou/geom/disppage0.json?v=2048-eef4"}],"materialPages":[{"first":0,"count":112,"url":"https://raw.githubusercontent.com/RSCSurf/SurfMaps3/main/maps/surf_fuckyou/materials/matpage0.json?v=2048-eef4"}],"brushModelPages":[{"first":0,"count":70,"url":"https://raw.githubusercontent.com/RSCSurf/SurfMaps3/main/maps/surf_fuckyou/geom/bsppage0.json?v=2048-eef4"}],"studioModelPages":[{"first":0,"count":0,"url":"https://raw.githubusercontent.com/RSCSurf/SurfMaps3/main/maps/surf_fuckyou/geom/mdlpage0.json?v=2048-eef4"}],"vertLightingPages":[{"first":0,"count":0,"url":"https://raw.githubusercontent.com/RSCSurf/SurfMaps3/main/maps/surf_fuckyou/geom/vhvpage0.json?v=2048-eef4"}],"visPages":[{"first":0,"count":2066,"url":"https://raw.githubusercontent.com/RSCSurf/SurfMaps3/main/maps/surf_fuckyou/geom/vispage0.json?v=2048-eef4"}],"ambientPages":[{"first":0,"count":4096,"url":"https://raw.githubusercontent.com/RSCSurf/SurfMaps3/main/maps/surf_fuckyou/geom/ambientpage0.json?v=2048-eef4"},{"first":4096,"count":1875,"url":"https://raw.githubusercontent.com/RSCSurf/SurfMaps3/main/maps/surf_fuckyou/geom/ambientpage1.json?v=2048-eef4"}],"entities":[{"skyMaterial":{"shader":"SourceUtils.Shaders.Sky","properties":[{"name":"cullFace","type":1,"value":false},{"name":"facePosX","type":4,"value":"https://raw.githubusercontent.com/RSCSurf/SurfMaps3/main/maps/surf_fuckyou/materials/skybox/sky_day02_05rt.vtf.json?v=2048-eef4"},{"name":"faceNegX","type":4,"value":"https://raw.githubusercontent.com/RSCSurf/SurfMaps3/main/maps/surf_fuckyou/materials/skybox/sky_day02_05lf.vtf.json?v=2048-eef4"},{"name":"facePosY","type":4,"value":"https://raw.githubusercontent.com/RSCSurf/SurfMaps3/main/maps/surf_fuckyou/materials/skybox/sky_day02_05bk.vtf.json?v=2048-eef4"},{"name":"faceNegY","type":4,"value":"https://raw.githubusercontent.com/RSCSurf/SurfMaps3/main/maps/surf_fuckyou/materials/skybox/sky_day02_05ft.vtf.json?v=2048-eef4"},{"name":"facePosZ","type":4,"value":"https://raw.githubusercontent.com/RSCSurf/SurfMaps3/main/maps/surf_fuckyou/materials/skybox/sky_day02_05up.vtf.json?v=2048-eef4"},{"name":"faceNegZ","type":4,"value":"https://raw.githubusercontent.com/RSCSurf/SurfMaps3/main/maps/surf_fuckyou/materials/skybox/sky_day02_05dn.vtf.json?v=2048-eef4"}]},"model":0,"classname":"worldspawn"},{"classname":"info_player_terrorist","origin":{"x":-5440.0,"y":8896.0,"z":-61.8471},"angles":{"x":0.0,"y":0.0,"z":0.0}},{"targetname":"tp_dest_b1","classname":"info_teleport_destination","origin":{"x":10976.0,"y":-10771.4,"z":-4568.0},"angles":{"x":0.0,"y":90.0,"z":0.0}},{"classname":"info_player_terrorist","origin":{"x":-11712.0,"y":4608.0,"z":-2239.0},"angles":{"x":0.0,"y":270.0,"z":0.0}},{"targetname":"zone_s4_start","classname":"trigger_multiple","origin":{"x":-11712.0,"y":5056.0,"z":-2048.0}},{"classname":"trigger_teleport","origin":{"x":-11712.0,"y":11168.0,"z":-7680.0}},{"classname":"trigger_teleport","origin":{"x":-14112.0,"y":7936.0,"z":2112.0}},{"classname":"trigger_teleport","origin":{"x":-10528.0,"y":11552.0,"z":2112.0}},{"classname":"trigger_teleport","origin":{"x":-10496.0,"y":4320.0,"z":2112.0}},{"classname":"trigger_teleport","origin":{"x":-6944.0,"y":7968.0,"z":2112.0}},{"targetname":"zone_s5_start","classname":"trigger_multiple","origin":{"x":-10496.0,"y":608.0,"z":7232.0}},{"classname":"light","origin":{"x":-6176.0,"y":8832.0,"z":128.0}},{"classname":"light","origin":{"x":-4640.0,"y":9024.0,"z":-995.592}},{"classname":"light","origin":{"x":-4128.0,"y":8512.0,"z":-1293.94}},{"classname":"light","origin":{"x":-2784.0,"y":8640.0,"z":-1688.5}},{"classname":"light","origin":{"x":-1440.0,"y":8896.0,"z":-1600.0}},{"classname":"light","origin":{"x":-2016.0,"y":8896.0,"z":-1441.92}},{"classname":"light","origin":{"x":-1824.0,"y":9088.0,"z":-1389.47}},{"classname":"light","origin":{"x":-1632.0,"y":8896.0,"z":-1375.8}},{"classname":"light","origin":{"x":-1824.0,"y":8704.0,"z":-1366.85}},{"classname":"light","origin":{"x":-5335.9,"y":8265.0,"z":-769.708}},{"classname":"light","origin":{"x":-5344.0,"y":9408.0,"z":-808.235}},{"classname":"light","origin":{"x":-6048.0,"y":8832.0,"z":-634.011}},{"classname":"light","origin":{"x":-5984.0,"y":8768.0,"z":-2155.17}},{"classname":"light","origin":{"x":-5408.0,"y":9280.0,"z":172.701}},{"classname":"light","origin":{"x":-5804.6,"y":8960.0,"z":128.0}},{"classname":"light","origin":{"x":-1312.0,"y":7552.0,"z":-1399.62}},{"classname":"light","origin":{"x":-1184.0,"y":7232.0,"z":-2368.0}},{"classname":"light","origin":{"x":-3680.0,"y":7680.0,"z":-1960.53}},{"classname":"light","origin":{"x":-6048.0,"y":6976.0,"z":-1856.0}},{"classname":"light","origin":{"x":-6451.3,"y":8055.0,"z":-2596.92}},{"classname":"light","origin":{"x":-4192.0,"y":7104.0,"z":-2451.2}},{"classname":"light","origin":{"x":-1504.0,"y":7168.0,"z":-1600.0}},{"classname":"light","origin":{"x":-4960.0,"y":7488.0,"z":-1587.59}},{"classname":"light","origin":{"x":-6944.0,"y":8448.0,"z":-1891.32}},{"classname":"light","origin":{"x":-6944.0,"y":9344.0,"z":-1519.71}},{"classname":"light","origin":{"x":-6752.0,"y":10624.0,"z":-1535.99}},{"classname":"light","origin":{"x":-5088.0,"y":10368.0,"z":-2240.0}},{"classname":"light","origin":{"x":-2272.0,"y":10432.0,"z":-1664.0}},{"classname":"light","origin":{"x":-6048.0,"y":9984.0,"z":-2396.54}},{"classname":"light","origin":{"x":-6048.0,"y":10368.0,"z":-1728.0}},{"classname":"light","origin":{"x":-1376.0,"y":10304.0,"z":-2112.0}},{"classname":"light","origin":{"x":-855.0,"y":8189.0,"z":-1686.11}},{"classname":"light","origin":{"x":-855.0,"y":9591.6,"z":-1676.21}},{"classname":"light","origin":{"x":-5664.0,"y":8640.0,"z":192.0}},{"targetname":"zone_s6_end","classname":"trigger_multiple","origin":{"x":-7072.0,"y":8896.0,"z":-1408.0}},{"targetname":"zone_s6_start","classname":"trigger_multiple","origin":{"x":-5856.0,"y":8896.0,"z":160.0}},{"targetname":"tp_dest_stage4","classname":"info_teleport_destination","origin":{"x":-11712.0,"y":5056.0,"z":-2096.0},"angles":{"x":0.0,"y":270.0,"z":0.0}},{"classname":"trigger_teleport","origin":{"x":-11712.0,"y":3040.0,"z":-4640.0}},{"classname":"trigger_teleport","origin":{"x":-11712.0,"y":320.0,"z":-5759.5}},{"classname":"trigger_teleport","origin":{"x":-10656.0,"y":2720.0,"z":-8063.0}},{"classname":"trigger_teleport","origin":{"x":-10592.0,"y":5024.0,"z":-8063.0}},{"classname":"trigger_teleport","origin":{"x":-12864.0,"y":5024.0,"z":-8063.0}},{"classname":"trigger_teleport","origin":{"x":-12768.0,"y":2752.0,"z":-8063.0}},{"classname":"trigger_teleport","origin":{"x":-11712.0,"y":5152.0,"z":-9215.0}},{"classname":"trigger_teleport","origin":{"x":-11712.0,"y":9056.0,"z":-9728.0}},{"classname":"trigger_teleport","origin":{"x":-9312.0,"y":1632.0,"z":-8063.0}},{"classname":"trigger_teleport","origin":{"x":-14112.0,"y":1632.0,"z":-8063.0}},{"targetname":"tp_dest_stage5","classname":"info_teleport_destination","origin":{"x":-10494.3,"y":320.0,"z":7248.0},"angles":{"x":0.0,"y":270.0,"z":0.0}},{"classname":"trigger_teleport","origin":{"x":-10496.0,"y":1472.0,"z":4288.0}},{"classname":"trigger_teleport","origin":{"x":-10496.0,"y":5792.0,"z":2976.0}},{"classname":"trigger_teleport","origin":{"x":-10496.0,"y":7936.0,"z":1376.0}},{"targetname":"tp_dest_stage6","classname":"info_teleport_destination","origin":{"x":-5504.0,"y":8892.0,"z":144.0},"angles":{"x":0.0,"y":0.0,"z":0.0}},{"classname":"trigger_teleport","origin":{"x":-5856.0,"y":8416.5,"z":160.0}},{"classname":"trigger_teleport","origin":{"x":-5856.0,"y":9376.5,"z":160.0}},{"classname":"trigger_teleport","origin":{"x":-3712.0,"y":8896.0,"z":-2656.0}},{"classname":"trigger_teleport","origin":{"x":-3840.0,"y":10432.0,"z":-2687.0}},{"classname":"trigger_teleport","origin":{"x":-3840.0,"y":7360.0,"z":-2687.0}},{"classname":"trigger_teleport","origin":{"x":-672.0,"y":8896.0,"z":-2687.0}},{"classname":"trigger_teleport","origin":{"x":-5664.0,"y":7296.0,"z":-2175.0}},{"classname":"trigger_teleport","origin":{"x":-5344.0,"y":7360.0,"z":-2424.0}},{"classname":"trigger_teleport","origin":{"x":-5664.0,"y":10432.0,"z":-2175.0}},{"classname":"trigger_teleport","origin":{"x":-5344.0,"y":10432.0,"z":-2424.0}},{"targetname":"tp_dest_stage1","classname":"info_teleport_destination","origin":{"x":4960.0,"y":9920.0,"z":-5808.0},"angles":{"x":0.0,"y":180.0,"z":0.0}},{"classname":"info_player_terrorist","origin":{"x":5184.0,"y":9928.1,"z":-5888.0},"angles":{"x":0.0,"y":180.0,"z":0.0}},{"targetname":"tp_dest_stage3","classname":"info_teleport_destination","origin":{"x":3776.0,"y":5696.0,"z":2496.0},"angles":{"x":0.0,"y":0.0,"z":0.0}},{"targetname":"tp_dest_stage2","classname":"info_teleport_destination","origin":{"x":1984.0,"y":-160.0,"z":-5648.0},"angles":{"x":0.0,"y":0.0,"z":0.0}},{"classname":"trigger_teleport","origin":{"x":1968.0,"y":-160.0,"z":-8543.0}},{"classname":"trigger_teleport","origin":{"x":4606.0,"y":-160.0,"z":-8815.0}},{"classname":"trigger_teleport","origin":{"x":7024.0,"y":-160.0,"z":-9087.0}},{"classname":"trigger_teleport","origin":{"x":6288.0,"y":-160.0,"z":-7935.0}},{"classname":"trigger_teleport","origin":{"x":3808.0,"y":-160.0,"z":-7431.6}},{"targetname":"zone_s2_start","classname":"trigger_multiple","origin":{"x":1984.0,"y":-160.0,"z":-5744.0}},{"classname":"trigger_teleport","origin":{"x":2944.0,"y":-160.0,"z":-6160.0}},{"classname":"trigger_teleport","origin":{"x":384.0,"y":-160.0,"z":-7216.0}},{"classname":"trigger_teleport","origin":{"x":6960.0,"y":9920.0,"z":-8686.0}},{"classname":"trigger_teleport","origin":{"x":6368.0,"y":9920.0,"z":-7631.0}},{"classname":"trigger_teleport","origin":{"x":2144.0,"y":9920.0,"z":-7760.0}},{"classname":"trigger_teleport","origin":{"x":7120.0,"y":5696.0,"z":1009.0}},{"classname":"trigger_teleport","origin":{"x":7536.0,"y":5696.0,"z":-239.0}},{"classname":"trigger_teleport","origin":{"x":12512.0,"y":5696.0,"z":177.0}},{"classname":"trigger_teleport","origin":{"x":9856.0,"y":5696.0,"z":-1327.0}},{"classname":"trigger_teleport","origin":{"x":14944.0,"y":5696.0,"z":-1391.0}},{"classname":"trigger_teleport","origin":{"x":8320.0,"y":5696.0,"z":-3935.0}},{"classname":"trigger_teleport","origin":{"x":2112.0,"y":5696.0,"z":-848.0}},{"classname":"trigger_teleport","origin":{"x":14944.0,"y":5696.0,"z":-751.0}},{"targetname":"zone_s3_start","classname":"trigger_multiple","origin":{"x":3776.0,"y":5696.0,"z":2400.0}},{"targetname":"zone_s1_start","classname":"trigger_multiple","origin":{"x":4960.0,"y":9920.0,"z":-5872.0}},{"classname":"trigger_teleport","origin":{"x":15452.5,"y":5696.0,"z":-751.0}},{"classname":"light","origin":{"x":4105.5,"y":9160.0,"z":-6969.65}},{"classname":"light","origin":{"x":3985.42,"y":9160.0,"z":-5711.74}},{"classname":"light","origin":{"x":5296.24,"y":10680.0,"z":-6862.7}},{"classname":"light","origin":{"x":7801.19,"y":9914.21,"z":-7766.0}},{"classname":"light","origin":{"x":8135.71,"y":9160.0,"z":-6611.5}},{"classname":"light","origin":{"x":8115.86,"y":10680.0,"z":-6718.51}},{"classname":"light","origin":{"x":8920.0,"y":9934.97,"z":-7028.12}},{"classname":"light","origin":{"x":9521.65,"y":10872.0,"z":-6590.93}},{"classname":"light","origin":{"x":10168.0,"y":10115.1,"z":-6531.05}},{"classname":"light","origin":{"x":9592.2,"y":8968.0,"z":-7174.12}},{"classname":"light","origin":{"x":10132.0,"y":10859.6,"z":-8406.0}},{"classname":"light","origin":{"x":9234.05,"y":8968.0,"z":-8259.98}},{"classname":"light","origin":{"x":8014.18,"y":8968.0,"z":-8096.12}},{"classname":"light","origin":{"x":7458.71,"y":10872.0,"z":-8072.0}},{"classname":"light","origin":{"x":5815.85,"y":8968.0,"z":-8191.85}},{"classname":"light","origin":{"x":5079.9,"y":9918.9,"z":-8886.0}},{"classname":"light","origin":{"x":4497.12,"y":10872.0,"z":-8135.3}},{"classname":"light","origin":{"x":3816.0,"y":9358.9,"z":-8243.32}},{"classname":"light","origin":{"x":3816.0,"y":10387.8,"z":-8016.83}},{"classname":"light","origin":{"x":3816.0,"y":10108.0,"z":-8729.75}},{"classname":"light","origin":{"x":2632.0,"y":9903.91,"z":-7945.51}},{"Brightness":{"R":255,"G":255,"B":255,"A":200},"Ambient":{"R":255,"G":255,"B":255,"A":94},"BrightnessHdr":{"R":255,"G":255,"B":255,"A":1},"AmbientHdr":{"R":255,"G":255,"B":255,"A":1},"BrightnessScaleHdr":1.0,"AmbientScaleHdr":1.0,"Pitch":0.0,"classname":"light_environment","origin":{"x":5008.11,"y":10335.3,"z":-6047.0},"angles":{"x":0.0,"y":75.0,"z":0.0}},{"classname":"trigger_teleport","origin":{"x":2608.0,"y":9920.0,"z":-8240.0}},{"classname":"light","origin":{"x":5985.64,"y":10872.0,"z":-8197.76}},{"classname":"light","origin":{"x":8455.07,"y":8968.0,"z":-8039.58}},{"classname":"light","origin":{"x":8479.45,"y":9362.44,"z":-8406.0}},{"classname":"light","origin":{"x":10168.0,"y":9638.53,"z":-7612.37}},{"classname":"light","origin":{"x":10168.0,"y":10566.1,"z":-7025.43}},{"classname":"light","origin":{"x":9000.0,"y":9767.58,"z":-7177.47}},{"classname":"light","origin":{"x":8370.36,"y":9818.04,"z":-6536.0}},{"classname":"light","origin":{"x":7879.34,"y":9160.0,"z":-6831.7}},{"classname":"light","origin":{"x":5992.0,"y":9961.43,"z":-7268.88}},{"classname":"light","origin":{"x":5113.69,"y":10680.0,"z":-6752.19}},{"classname":"light","origin":{"x":4508.42,"y":9160.0,"z":-6615.38}},{"classname":"light","origin":{"x":5432.0,"y":9606.08,"z":-5858.89}},{"classname":"light","origin":{"x":4792.73,"y":10414.8,"z":-6040.0}},{"classname":"light","origin":{"x":4628.23,"y":9580.64,"z":-6040.0}},{"classname":"light","origin":{"x":6422.58,"y":-1272.0,"z":-7583.94}},{"classname":"light","origin":{"x":5960.52,"y":952.0,"z":-7541.26}},{"classname":"light","origin":{"x":6271.45,"y":27.1426,"z":-7336.0}},{"classname":"light","origin":{"x":7392.56,"y":952.0,"z":-7520.84}},{"classname":"light","origin":{"x":7416.0,"y":-106.637,"z":-7635.42}},{"classname":"light","origin":{"x":8625.38,"y":528.65,"z":-7815.63}},{"classname":"light","origin":{"x":8665.49,"y":473.986,"z":-8569.26}},{"classname":"light","origin":{"x":8468.79,"y":-980.037,"z":-8760.21}},{"classname":"light","origin":{"x":8385.24,"y":-228.372,"z":-8749.46}},{"classname":"light","origin":{"x":7392.17,"y":-1272.0,"z":-8720.21}},{"classname":"light","origin":{"x":6353.04,"y":-1272.0,"z":-8366.0}},{"classname":"light","origin":{"x":7416.0,"y":-284.015,"z":-8604.56}},{"classname":"light","origin":{"x":6929.55,"y":952.0,"z":-8379.72}},{"classname":"light","origin":{"x":5475.34,"y":952.0,"z":-8503.42}},{"classname":"light","origin":{"x":4021.03,"y":-155.474,"z":-8360.88}},{"classname":"light","origin":{"x":5527.33,"y":-1272.0,"z":-8201.95}},{"classname":"light","origin":{"x":4262.21,"y":-1546.3,"z":-8631.11}},{"classname":"light","origin":{"x":3634.12,"y":-1912.0,"z":-7993.06}},{"classname":"light","origin":{"x":4422.46,"y":-1439.79,"z":-8711.23}},{"classname":"light","origin":{"x":2716.35,"y":-1912.0,"z":-7652.65}},{"classname":"light","origin":{"x":378.365,"y":-1912.0,"z":-7138.09}},{"classname":"light","origin":{"x":-120.0,"y":-1365.41,"z":-7252.75}},{"classname":"light","origin":{"x":1219.28,"y":1592.0,"z":-7543.24}},{"classname":"light","origin":{"x":-120.0,"y":1560.78,"z":-6666.58}},{"classname":"light","origin":{"x":10907.8,"y":5702.74,"z":1608.0}},{"classname":"light","origin":{"x":11535.5,"y":7736.0,"z":953.122}},{"classname":"light","origin":{"x":11672.0,"y":5447.11,"z":1081.36}},{"classname":"light","origin":{"x":11353.4,"y":3656.0,"z":-18.5767}},{"classname":"light","origin":{"x":10269.0,"y":4930.78,"z":-258.95}},{"classname":"light","origin":{"x":9991.16,"y":6932.91,"z":-536.841}},{"classname":"light","origin":{"x":12569.3,"y":7736.0,"z":-71.2217}},{"classname":"light","origin":{"x":14902.9,"y":6809.08,"z":-2.31543}},{"classname":"light","origin":{"x":14947.5,"y":5686.46,"z":-742.0}},{"classname":"light","origin":{"x":15049.9,"y":5525.46,"z":-1087.72}},{"classname":"light","origin":{"x":14919.7,"y":6001.76,"z":-1382.0}},{"classname":"light","origin":{"x":14881.1,"y":5417.69,"z":-2022.0}},{"classname":"light","origin":{"x":14850.3,"y":6044.65,"z":-2022.0}},{"classname":"light","origin":{"x":15416.0,"y":5496.13,"z":-2247.63}},{"classname":"light","origin":{"x":14809.7,"y":6486.29,"z":-2580.69}},{"classname":"light","origin":{"x":14464.7,"y":4560.66,"z":-2977.96}},{"classname":"light","origin":{"x":14061.6,"y":7234.38,"z":-3576.77}},{"classname":"light","origin":{"x":12746.7,"y":7736.0,"z":-3668.75}},{"classname":"light","origin":{"x":12953.0,"y":3656.0,"z":-3570.93}},{"classname":"light","origin":{"x":11863.0,"y":3656.0,"z":-4272.18}},{"classname":"light","origin":{"x":11368.6,"y":7736.0,"z":-3738.84}},{"classname":"light","origin":{"x":7551.65,"y":7736.0,"z":-3652.37}},{"classname":"light","origin":{"x":6224.09,"y":3656.0,"z":-3777.72}},{"classname":"light","origin":{"x":4616.0,"y":4697.11,"z":-3020.43}},{"classname":"light","origin":{"x":4900.44,"y":3656.0,"z":-1601.31}},{"classname":"light","origin":{"x":5597.84,"y":6552.08,"z":-1108.27}},{"classname":"light","origin":{"x":4169.88,"y":7247.7,"z":-344.0}},{"classname":"light","origin":{"x":3684.39,"y":3656.0,"z":-530.171}},{"classname":"light","origin":{"x":2560.01,"y":5447.44,"z":-344.0}},{"classname":"light","origin":{"x":2114.9,"y":6333.23,"z":-344.0}},{"classname":"light","origin":{"x":-10248.0,"y":3676.47,"z":-2174.09}},{"classname":"light","origin":{"x":-11690.7,"y":2696.0,"z":-2562.7}},{"classname":"light","origin":{"x":-12173.3,"y":2696.0,"z":-1884.31}},{"classname":"light","origin":{"x":-13176.0,"y":4404.16,"z":-2824.28}},{"classname":"light","origin":{"x":-13176.0,"y":2757.54,"z":-2758.31}},{"classname":"light","origin":{"x":-13176.0,"y":2023.09,"z":-2210.44}},{"classname":"light","origin":{"x":-12232.0,"y":2645.94,"z":-2711.2}},{"classname":"light","origin":{"x":-12962.3,"y":-184.0,"z":-3113.21}},{"classname":"light","origin":{"x":-11561.4,"y":-184.0,"z":-3120.77}},{"classname":"light","origin":{"x":-10248.0,"y":1394.29,"z":-2972.86}},{"classname":"light","origin":{"x":-10248.0,"y":2894.3,"z":-4009.73}},{"classname":"light","origin":{"x":-10248.0,"y":423.212,"z":-2167.59}},{"classname":"light","origin":{"x":-11137.6,"y":-184.0,"z":-4918.27}},{"classname":"light","origin":{"x":-12693.6,"y":1122.25,"z":-4600.0}},{"classname":"light","origin":{"x":-10359.9,"y":943.84,"z":-4600.0}},{"classname":"light","origin":{"x":-9977.33,"y":11.124,"z":-5013.48}},{"classname":"light","origin":{"x":-11312.0,"y":1400.0,"z":-5272.51}},{"classname":"light","origin":{"x":-14009.6,"y":530.751,"z":-5346.13}},{"classname":"light","origin":{"x":-8564.2,"y":1530.29,"z":-6105.98}},{"classname":"light","origin":{"x":-9710.73,"y":2897.31,"z":-6689.76}},{"classname":"light","origin":{"x":-9489.74,"y":2633.83,"z":-4893.3}},{"classname":"light","origin":{"x":-10872.5,"y":2255.58,"z":-5032.53}},{"classname":"light","origin":{"x":-10772.0,"y":3747.06,"z":-5458.67}},{"classname":"light","origin":{"x":-14526.5,"y":1927.72,"z":-5631.71}},{"classname":"light","origin":{"x":-13571.7,"y":3066.13,"z":-6817.65}},{"classname":"light","origin":{"x":-14526.5,"y":1927.66,"z":-7766.26}},{"classname":"light","origin":{"x":-13240.0,"y":5886.04,"z":-6649.5}},{"classname":"light","origin":{"x":-13240.0,"y":3688.03,"z":-7533.41}},{"classname":"light","origin":{"x":-13240.0,"y":4101.3,"z":-5836.04}},{"classname":"light","origin":{"x":-12996.6,"y":2959.61,"z":-8054.0}},{"classname":"light","origin":{"x":-10361.4,"y":5604.83,"z":-8054.0}},{"classname":"light","origin":{"x":-11624.7,"y":5496.0,"z":-9022.02}},{"classname":"light","origin":{"x":-11643.2,"y":11126.4,"z":-7928.0}},{"classname":"light","origin":{"x":-10522.8,"y":604.204,"z":6984.0}},{"classname":"light","origin":{"x":-10507.3,"y":1080.0,"z":7448.33}},{"classname":"light","origin":{"x":-9378.12,"y":-1272.0,"z":6553.41}},{"classname":"light","origin":{"x":-8968.0,"y":-198.623,"z":6783.31}},{"classname":"light","origin":{"x":-12024.0,"y":-610.857,"z":6459.0}},{"classname":"light","origin":{"x":-11350.1,"y":-1272.0,"z":7038.88}},{"classname":"light","origin":{"x":-12024.0,"y":1017.58,"z":5643.14}},{"classname":"light","origin":{"x":-12024.0,"y":2608.06,"z":5973.25}},{"classname":"light","origin":{"x":-12024.0,"y":3551.11,"z":4225.78}},{"classname":"light","origin":{"x":-8968.0,"y":1545.06,"z":4988.05}},{"classname":"light","origin":{"x":-8968.0,"y":3713.66,"z":4062.13}},{"classname":"light","origin":{"x":-8968.0,"y":1976.43,"z":6489.31}},{"classname":"light","origin":{"x":-8968.0,"y":-582.729,"z":7320.19}},{"classname":"light","origin":{"x":-8968.0,"y":4910.77,"z":4309.99}},{"classname":"light","origin":{"x":-9494.34,"y":6712.0,"z":4315.94}},{"classname":"light","origin":{"x":-10690.0,"y":6712.0,"z":4146.56}},{"classname":"light","origin":{"x":-12246.7,"y":5796.78,"z":3870.42}},{"classname":"light","origin":{"x":-12195.4,"y":5632.67,"z":5028.0}},{"classname":"light","origin":{"x":-12276.7,"y":7070.77,"z":5009.21}},{"classname":"light","origin":{"x":-10530.1,"y":6712.0,"z":5354.51}},{"classname":"light","origin":{"x":-11881.7,"y":7416.0,"z":5456.27}},{"classname":"light","origin":{"x":-11109.0,"y":7416.0,"z":4926.42}},{"classname":"light","origin":{"x":-10828.8,"y":6856.0,"z":5329.13}},{"classname":"light","origin":{"x":-10588.1,"y":8440.0,"z":5387.42}},{"classname":"light","origin":{"x":-11064.0,"y":7767.39,"z":5252.43}},{"classname":"light","origin":{"x":-10507.8,"y":7925.5,"z":2884.3}},{"classname":"light","origin":{"x":-11000.0,"y":7972.64,"z":4124.24}},{"classname":"light","origin":{"x":-10061.4,"y":8440.0,"z":4645.71}},{"classname":"light","origin":{"x":-12586.2,"y":10261.1,"z":1416.0}},{"classname":"light","origin":{"x":-14072.0,"y":9414.02,"z":1909.66}},{"classname":"light","origin":{"x":-11298.8,"y":11512.0,"z":2380.5}},{"classname":"light","origin":{"x":-9988.96,"y":11512.0,"z":2366.85}},{"classname":"light","origin":{"x":-8888.37,"y":10878.1,"z":1416.0}},{"classname":"light","origin":{"x":-6984.0,"y":10961.0,"z":2129.48}},{"classname":"light","origin":{"x":-8358.61,"y":11512.0,"z":2172.69}},{"classname":"light","origin":{"x":-8002.47,"y":8408.33,"z":1416.0}},{"classname":"light","origin":{"x":-6984.0,"y":7431.09,"z":2390.98}},{"classname":"light","origin":{"x":-8360.84,"y":4839.63,"z":1416.0}},{"classname":"light","origin":{"x":-10242.6,"y":4360.0,"z":2153.09}},{"classname":"light","origin":{"x":-10238.7,"y":7346.54,"z":1416.0}},{"classname":"light","origin":{"x":-12940.3,"y":4360.0,"z":2337.05}},{"classname":"light","origin":{"x":-14072.0,"y":5947.69,"z":2335.47}},{"classname":"light","origin":{"x":-12759.3,"y":7297.99,"z":1416.0}},{"classname":"light","origin":{"x":-7158.64,"y":8200.0,"z":-1331.8}},{"classname":"light","origin":{"x":-7160.0,"y":9280.92,"z":-1913.04}},{"targetname":"zone_bonus1_start","classname":"trigger_multiple","origin":{"x":10976.0,"y":-10688.0,"z":-4608.0}},{"classname":"trigger_teleport","origin":{"x":10976.0,"y":-10496.0,"z":-5599.0}},{"classname":"trigger_teleport","origin":{"x":10976.0,"y":-10496.0,"z":-5599.0}},{"targetname":"zone_bonus1_end","classname":"trigger_multiple","origin":{"x":10976.0,"y":-11040.0,"z":-14688.0}},{"classname":"trigger_teleport","origin":{"x":11008.0,"y":-13248.0,"z":-8256.0}},{"targetname":"b1f1","classname":"filter_activator_name","origin":{"x":11263.0,"y":-13857.0,"z":-6518.0}},{"targetname":"b1f2","classname":"filter_activator_name","origin":{"x":11195.6,"y":-13861.5,"z":-6518.0}},{"classname":"trigger_teleport","origin":{"x":11249.1,"y":-13631.0,"z":-7424.0}},{"classname":"trigger_multiple","origin":{"x":11168.0,"y":-14047.0,"z":-7424.0}},{"classname":"light","origin":{"x":10312.7,"y":-11000.0,"z":-4486.37}},{"classname":"light","origin":{"x":11210.0,"y":-10642.7,"z":-4760.0}},{"classname":"light","origin":{"x":11736.0,"y":-10068.9,"z":-4507.64}},{"classname":"light","origin":{"x":10216.0,"y":-10027.6,"z":-5029.79}},{"classname":"light","origin":{"x":10443.9,"y":-10996.6,"z":-5590.0}},{"classname":"light","origin":{"x":12638.4,"y":-12501.9,"z":-6633.01}},{"classname":"light","origin":{"x":12019.6,"y":-10645.6,"z":-6064.09}},{"classname":"light","origin":{"x":10975.8,"y":-9480.0,"z":-7226.47}},{"classname":"light","origin":{"x":9883.23,"y":-10793.0,"z":-7121.9}},{"classname":"light","origin":{"x":9325.63,"y":-12465.8,"z":-6606.41}},{"classname":"light","origin":{"x":12834.7,"y":-13090.7,"z":-7437.3}},{"classname":"light","origin":{"x":13016.0,"y":-13768.1,"z":-6090.77}},{"classname":"light","origin":{"x":11246.7,"y":-15512.0,"z":-6046.25}},{"classname":"light","origin":{"x":9901.13,"y":-15113.3,"z":-8214.0}},{"classname":"light","origin":{"x":13016.0,"y":-15028.9,"z":-8034.04}},{"classname":"light","origin":{"x":10641.0,"y":-13040.9,"z":-8216.0}},{"classname":"light","origin":{"x":10837.7,"y":-11651.0,"z":-9302.0}},{"classname":"light","origin":{"x":8168.0,"y":-10937.2,"z":-8414.17}},{"classname":"light","origin":{"x":10317.6,"y":-9288.0,"z":-9706.42}},{"classname":"light","origin":{"x":12506.8,"y":-11461.4,"z":-9750.0}},{"classname":"light","origin":{"x":10955.3,"y":-10824.0,"z":-10479.9}},{"classname":"info_player_terrorist","origin":{"x":4959.34,"y":10088.3,"z":-6045.0},"angles":{"x":0.0,"y":180.0,"z":0.0}},{"classname":"info_player_terrorist","origin":{"x":4953.99,"y":10153.1,"z":-6045.0},"angles":{"x":0.0,"y":180.0,"z":0.0}},{"classname":"info_player_terrorist","origin":{"x":4953.59,"y":10213.7,"z":-6045.0},"angles":{"x":0.0,"y":180.0,"z":0.0}},{"classname":"info_player_terrorist","origin":{"x":4953.22,"y":10258.2,"z":-6045.0},"angles":{"x":0.0,"y":180.0,"z":0.0}},{"classname":"info_player_terrorist","origin":{"x":4952.97,"y":10303.3,"z":-6045.0},"angles":{"x":0.0,"y":180.0,"z":0.0}},{"classname":"info_player_terrorist","origin":{"x":4952.36,"y":10389.5,"z":-6045.0},"angles":{"x":0.0,"y":180.0,"z":0.0}},{"classname":"info_player_terrorist","origin":{"x":4951.59,"y":10443.3,"z":-6045.0},"angles":{"x":0.0,"y":180.0,"z":0.0}},{"classname":"info_player_terrorist","origin":{"x":4950.76,"y":10502.8,"z":-6045.0},"angles":{"x":0.0,"y":180.0,"z":0.0}},{"classname":"info_player_terrorist","origin":{"x":4949.94,"y":10562.7,"z":-6045.0},"angles":{"x":0.0,"y":180.0,"z":0.0}},{"classname":"info_player_terrorist","origin":{"x":4948.66,"y":10649.4,"z":-6045.0},"angles":{"x":0.0,"y":180.0,"z":0.0}},{"classname":"info_player_terrorist","origin":{"x":5026.46,"y":10654.7,"z":-6046.0},"angles":{"x":0.0,"y":180.0,"z":0.0}},{"classname":"info_player_terrorist","origin":{"x":5027.74,"y":10568.1,"z":-6046.0},"angles":{"x":0.0,"y":180.0,"z":0.0}},{"classname":"info_player_terrorist","origin":{"x":5028.56,"y":10508.1,"z":-6046.0},"angles":{"x":0.0,"y":180.0,"z":0.0}},{"classname":"info_player_terrorist","origin":{"x":5029.39,"y":10448.6,"z":-6046.0},"angles":{"x":0.0,"y":180.0,"z":0.0}},{"classname":"info_player_terrorist","origin":{"x":5030.16,"y":10394.8,"z":-6046.0},"angles":{"x":0.0,"y":180.0,"z":0.0}},{"classname":"info_player_terrorist","origin":{"x":5030.77,"y":10308.6,"z":-6046.0},"angles":{"x":0.0,"y":180.0,"z":0.0}},{"classname":"info_player_terrorist","origin":{"x":5031.02,"y":10263.5,"z":-6046.0},"angles":{"x":0.0,"y":180.0,"z":0.0}},{"classname":"info_player_terrorist","origin":{"x":5031.39,"y":10219.0,"z":-6046.0},"angles":{"x":0.0,"y":180.0,"z":0.0}},{"classname":"info_player_terrorist","origin":{"x":5031.79,"y":10158.4,"z":-6046.0},"angles":{"x":0.0,"y":180.0,"z":0.0}},{"classname":"info_player_terrorist","origin":{"x":5037.14,"y":10093.7,"z":-6046.0},"angles":{"x":0.0,"y":180.0,"z":0.0}},{"classname":"info_player_terrorist","origin":{"x":5092.5,"y":10625.0,"z":-6046.0},"angles":{"x":0.0,"y":180.0,"z":0.0}},{"classname":"info_player_terrorist","origin":{"x":5093.77,"y":10538.4,"z":-6046.0},"angles":{"x":0.0,"y":180.0,"z":0.0}},{"classname":"info_player_terrorist","origin":{"x":5094.59,"y":10478.5,"z":-6046.0},"angles":{"x":0.0,"y":180.0,"z":0.0}},{"classname":"info_player_terrorist","origin":{"x":5095.42,"y":10419.0,"z":-6046.0},"angles":{"x":0.0,"y":180.0,"z":0.0}},{"classname":"info_player_terrorist","origin":{"x":5096.19,"y":10365.1,"z":-6046.0},"angles":{"x":0.0,"y":180.0,"z":0.0}},{"classname":"info_player_terrorist","origin":{"x":5096.8,"y":10278.9,"z":-6046.0},"angles":{"x":0.0,"y":180.0,"z":0.0}},{"classname":"info_player_terrorist","origin":{"x":5097.05,"y":10233.9,"z":-6046.0},"angles":{"x":0.0,"y":180.0,"z":0.0}},{"classname":"info_player_terrorist","origin":{"x":5097.43,"y":10189.4,"z":-6046.0},"angles":{"x":0.0,"y":180.0,"z":0.0}},{"classname":"info_player_terrorist","origin":{"x":5097.83,"y":10128.8,"z":-6046.0},"angles":{"x":0.0,"y":180.0,"z":0.0}},{"classname":"info_player_terrorist","origin":{"x":5103.17,"y":10064.0,"z":-6046.0},"angles":{"x":0.0,"y":180.0,"z":0.0}},{"classname":"info_player_terrorist","origin":{"x":5194.81,"y":10657.3,"z":-6046.0},"angles":{"x":0.0,"y":180.0,"z":0.0}},{"classname":"info_player_terrorist","origin":{"x":5196.08,"y":10570.6,"z":-6046.0},"angles":{"x":0.0,"y":180.0,"z":0.0}},{"classname":"info_player_terrorist","origin":{"x":5196.9,"y":10510.7,"z":-6046.0},"angles":{"x":0.0,"y":180.0,"z":0.0}},{"classname":"info_player_terrorist","origin":{"x":5197.73,"y":10451.2,"z":-6046.0},"angles":{"x":0.0,"y":180.0,"z":0.0}},{"classname":"info_player_terrorist","origin":{"x":5198.5,"y":10397.4,"z":-6046.0},"angles":{"x":0.0,"y":180.0,"z":0.0}},{"classname":"info_player_terrorist","origin":{"x":5199.11,"y":10311.2,"z":-6046.0},"angles":{"x":0.0,"y":180.0,"z":0.0}},{"classname":"info_player_terrorist","origin":{"x":5199.37,"y":10266.1,"z":-6046.0},"angles":{"x":0.0,"y":180.0,"z":0.0}},{"classname":"info_player_terrorist","origin":{"x":5199.74,"y":10221.6,"z":-6046.0},"angles":{"x":0.0,"y":180.0,"z":0.0}},{"classname":"info_player_terrorist","origin":{"x":5200.14,"y":10161.0,"z":-6046.0},"angles":{"x":0.0,"y":180.0,"z":0.0}},{"classname":"info_player_terrorist","origin":{"x":5205.48,"y":10096.2,"z":-6046.0},"angles":{"x":0.0,"y":180.0,"z":0.0}},{"classname":"info_player_terrorist","origin":{"x":5267.66,"y":10655.7,"z":-6046.0},"angles":{"x":0.0,"y":180.0,"z":0.0}},{"classname":"info_player_terrorist","origin":{"x":5268.93,"y":10569.1,"z":-6046.0},"angles":{"x":0.0,"y":180.0,"z":0.0}},{"classname":"info_player_terrorist","origin":{"x":5269.75,"y":10509.2,"z":-6046.0},"angles":{"x":0.0,"y":180.0,"z":0.0}},{"classname":"info_player_terrorist","origin":{"x":5270.58,"y":10449.7,"z":-6046.0},"angles":{"x":0.0,"y":180.0,"z":0.0}},{"classname":"info_player_terrorist","origin":{"x":5271.35,"y":10395.8,"z":-6046.0},"angles":{"x":0.0,"y":180.0,"z":0.0}},{"classname":"info_player_terrorist","origin":{"x":5271.96,"y":10309.7,"z":-6046.0},"angles":{"x":0.0,"y":180.0,"z":0.0}},{"classname":"info_player_terrorist","origin":{"x":5272.21,"y":10264.6,"z":-6046.0},"angles":{"x":0.0,"y":180.0,"z":0.0}},{"classname":"info_player_terrorist","origin":{"x":5272.59,"y":10220.1,"z":-6046.0},"angles":{"x":0.0,"y":180.0,"z":0.0}},{"classname":"info_player_terrorist","origin":{"x":5272.98,"y":10159.5,"z":-6046.0},"angles":{"x":0.0,"y":180.0,"z":0.0}},{"classname":"info_player_terrorist","origin":{"x":5278.33,"y":10094.7,"z":-6046.0},"angles":{"x":0.0,"y":180.0,"z":0.0}},{"classname":"info_player_terrorist","origin":{"x":5367.32,"y":10653.2,"z":-6046.0},"angles":{"x":0.0,"y":180.0,"z":0.0}},{"classname":"info_player_terrorist","origin":{"x":5368.6,"y":10566.5,"z":-6046.0},"angles":{"x":0.0,"y":180.0,"z":0.0}},{"classname":"info_player_terrorist","origin":{"x":5369.42,"y":10506.6,"z":-6046.0},"angles":{"x":0.0,"y":180.0,"z":0.0}},{"classname":"info_player_terrorist","origin":{"x":5370.25,"y":10447.1,"z":-6046.0},"angles":{"x":0.0,"y":180.0,"z":0.0}},{"classname":"info_player_terrorist","origin":{"x":5371.02,"y":10393.3,"z":-6046.0},"angles":{"x":0.0,"y":180.0,"z":0.0}},{"classname":"info_player_terrorist","origin":{"x":5371.63,"y":10307.1,"z":-6046.0},"angles":{"x":0.0,"y":180.0,"z":0.0}},{"classname":"info_player_terrorist","origin":{"x":5371.88,"y":10262.0,"z":-6046.0},"angles":{"x":0.0,"y":180.0,"z":0.0}},{"classname":"info_player_terrorist","origin":{"x":5372.25,"y":10217.5,"z":-6046.0},"angles":{"x":0.0,"y":180.0,"z":0.0}},{"classname":"info_player_terrorist","origin":{"x":5372.65,"y":10156.9,"z":-6046.0},"angles":{"x":0.0,"y":180.0,"z":0.0}},{"classname":"info_player_terrorist","origin":{"x":5378.0,"y":10092.1,"z":-6046.0},"angles":{"x":0.0,"y":180.0,"z":0.0}},{"classname":"info_player_counterterrorist","origin":{"x":4914.67,"y":9257.06,"z":-6047.0},"angles":{"x":0.0,"y":180.0,"z":0.0}},{"classname":"info_player_counterterrorist","origin":{"x":4909.33,"y":9321.82,"z":-6047.0},"angles":{"x":0.0,"y":180.0,"z":0.0}},{"classname":"info_player_counterterrorist","origin":{"x":4908.93,"y":9382.42,"z":-6047.0},"angles":{"x":0.0,"y":180.0,"z":0.0}},{"classname":"info_player_counterterrorist","origin":{"x":4908.56,"y":9426.91,"z":-6047.0},"angles":{"x":0.0,"y":180.0,"z":0.0}},{"classname":"info_player_counterterrorist","origin":{"x":4908.31,"y":9472.01,"z":-6047.0},"angles":{"x":0.0,"y":180.0,"z":0.0}},{"classname":"info_player_counterterrorist","origin":{"x":4907.7,"y":9558.19,"z":-6047.0},"angles":{"x":0.0,"y":180.0,"z":0.0}},{"classname":"info_player_counterterrorist","origin":{"x":4906.93,"y":9612.04,"z":-6047.0},"angles":{"x":0.0,"y":180.0,"z":0.0}},{"classname":"info_player_counterterrorist","origin":{"x":4906.1,"y":9671.51,"z":-6047.0},"angles":{"x":0.0,"y":180.0,"z":0.0}},{"classname":"info_player_counterterrorist","origin":{"x":4905.28,"y":9731.46,"z":-6047.0},"angles":{"x":0.0,"y":180.0,"z":0.0}},{"classname":"info_player_counterterrorist","origin":{"x":4904.0,"y":9818.1,"z":-6047.0},"angles":{"x":0.0,"y":180.0,"z":0.0}},{"classname":"info_player_counterterrorist","origin":{"x":4981.8,"y":9823.44,"z":-6048.0},"angles":{"x":0.0,"y":180.0,"z":0.0}},{"classname":"info_player_counterterrorist","origin":{"x":4983.08,"y":9736.8,"z":-6048.0},"angles":{"x":0.0,"y":180.0,"z":0.0}},{"classname":"info_player_counterterrorist","origin":{"x":4983.9,"y":9676.85,"z":-6048.0},"angles":{"x":0.0,"y":180.0,"z":0.0}},{"classname":"info_player_counterterrorist","origin":{"x":4984.73,"y":9617.38,"z":-6048.0},"angles":{"x":0.0,"y":180.0,"z":0.0}},{"classname":"info_player_counterterrorist","origin":{"x":4985.5,"y":9563.54,"z":-6048.0},"angles":{"x":0.0,"y":180.0,"z":0.0}},{"classname":"info_player_counterterrorist","origin":{"x":4986.11,"y":9477.35,"z":-6048.0},"angles":{"x":0.0,"y":180.0,"z":0.0}},{"classname":"info_player_counterterrorist","origin":{"x":4986.36,"y":9432.25,"z":-6048.0},"angles":{"x":0.0,"y":180.0,"z":0.0}},{"classname":"info_player_counterterrorist","origin":{"x":4986.73,"y":9387.76,"z":-6048.0},"angles":{"x":0.0,"y":180.0,"z":0.0}},{"classname":"info_player_counterterrorist","origin":{"x":4987.13,"y":9327.16,"z":-6048.0},"angles":{"x":0.0,"y":180.0,"z":0.0}},{"classname":"info_player_counterterrorist","origin":{"x":4992.48,"y":9262.4,"z":-6048.0},"angles":{"x":0.0,"y":180.0,"z":0.0}},{"classname":"info_player_counterterrorist","origin":{"x":5047.83,"y":9793.77,"z":-6048.0},"angles":{"x":0.0,"y":180.0,"z":0.0}},{"classname":"info_player_counterterrorist","origin":{"x":5049.11,"y":9707.13,"z":-6048.0},"angles":{"x":0.0,"y":180.0,"z":0.0}},{"classname":"info_player_counterterrorist","origin":{"x":5049.93,"y":9647.18,"z":-6048.0},"angles":{"x":0.0,"y":180.0,"z":0.0}},{"classname":"info_player_counterterrorist","origin":{"x":5050.76,"y":9587.71,"z":-6048.0},"angles":{"x":0.0,"y":180.0,"z":0.0}},{"classname":"info_player_counterterrorist","origin":{"x":5051.53,"y":9533.87,"z":-6048.0},"angles":{"x":0.0,"y":180.0,"z":0.0}},{"classname":"info_player_counterterrorist","origin":{"x":5052.14,"y":9447.68,"z":-6048.0},"angles":{"x":0.0,"y":180.0,"z":0.0}},{"classname":"info_player_counterterrorist","origin":{"x":5052.39,"y":9402.58,"z":-6048.0},"angles":{"x":0.0,"y":180.0,"z":0.0}},{"classname":"info_player_counterterrorist","origin":{"x":5052.76,"y":9358.09,"z":-6048.0},"angles":{"x":0.0,"y":180.0,"z":0.0}},{"classname":"info_player_counterterrorist","origin":{"x":5053.17,"y":9297.49,"z":-6048.0},"angles":{"x":0.0,"y":180.0,"z":0.0}},{"classname":"info_player_counterterrorist","origin":{"x":5058.51,"y":9232.73,"z":-6048.0},"angles":{"x":0.0,"y":180.0,"z":0.0}},{"classname":"info_player_counterterrorist","origin":{"x":5150.15,"y":9826.0,"z":-6048.0},"angles":{"x":0.0,"y":180.0,"z":0.0}},{"classname":"info_player_counterterrorist","origin":{"x":5151.42,"y":9739.36,"z":-6048.0},"angles":{"x":0.0,"y":180.0,"z":0.0}},{"classname":"info_player_counterterrorist","origin":{"x":5152.24,"y":9679.41,"z":-6048.0},"angles":{"x":0.0,"y":180.0,"z":0.0}},{"classname":"info_player_counterterrorist","origin":{"x":5153.07,"y":9619.94,"z":-6048.0},"angles":{"x":0.0,"y":180.0,"z":0.0}},{"classname":"info_player_counterterrorist","origin":{"x":5153.84,"y":9566.1,"z":-6048.0},"angles":{"x":0.0,"y":180.0,"z":0.0}},{"classname":"info_player_counterterrorist","origin":{"x":5154.45,"y":9479.91,"z":-6048.0},"angles":{"x":0.0,"y":180.0,"z":0.0}},{"classname":"info_player_counterterrorist","origin":{"x":5154.71,"y":9434.81,"z":-6048.0},"angles":{"x":0.0,"y":180.0,"z":0.0}},{"classname":"info_player_counterterrorist","origin":{"x":5155.08,"y":9390.32,"z":-6048.0},"angles":{"x":0.0,"y":180.0,"z":0.0}},{"classname":"info_player_counterterrorist","origin":{"x":5155.48,"y":9329.72,"z":-6048.0},"angles":{"x":0.0,"y":180.0,"z":0.0}},{"classname":"info_player_counterterrorist","origin":{"x":5160.82,"y":9264.96,"z":-6048.0},"angles":{"x":0.0,"y":180.0,"z":0.0}},{"classname":"info_player_counterterrorist","origin":{"x":5223.0,"y":9824.47,"z":-6048.0},"angles":{"x":0.0,"y":180.0,"z":0.0}},{"classname":"info_player_counterterrorist","origin":{"x":5224.27,"y":9737.84,"z":-6048.0},"angles":{"x":0.0,"y":180.0,"z":0.0}},{"classname":"info_player_counterterrorist","origin":{"x":5225.09,"y":9677.88,"z":-6048.0},"angles":{"x":0.0,"y":180.0,"z":0.0}},{"classname":"info_player_counterterrorist","origin":{"x":5225.92,"y":9618.41,"z":-6048.0},"angles":{"x":0.0,"y":180.0,"z":0.0}},{"classname":"info_player_counterterrorist","origin":{"x":5226.69,"y":9564.57,"z":-6048.0},"angles":{"x":0.0,"y":180.0,"z":0.0}},{"classname":"info_player_counterterrorist","origin":{"x":5227.3,"y":9478.38,"z":-6048.0},"angles":{"x":0.0,"y":180.0,"z":0.0}},{"classname":"info_player_counterterrorist","origin":{"x":5227.55,"y":9433.28,"z":-6048.0},"angles":{"x":0.0,"y":180.0,"z":0.0}},{"classname":"info_player_counterterrorist","origin":{"x":5227.92,"y":9388.79,"z":-6048.0},"angles":{"x":0.0,"y":180.0,"z":0.0}},{"classname":"info_player_counterterrorist","origin":{"x":5228.32,"y":9328.19,"z":-6048.0},"angles":{"x":0.0,"y":180.0,"z":0.0}},{"classname":"info_player_counterterrorist","origin":{"x":5233.67,"y":9263.43,"z":-6048.0},"angles":{"x":0.0,"y":180.0,"z":0.0}},{"classname":"info_player_counterterrorist","origin":{"x":5322.66,"y":9821.91,"z":-6048.0},"angles":{"x":0.0,"y":180.0,"z":0.0}},{"classname":"info_player_counterterrorist","origin":{"x":5323.94,"y":9735.27,"z":-6048.0},"angles":{"x":0.0,"y":180.0,"z":0.0}},{"classname":"info_player_counterterrorist","origin":{"x":5324.76,"y":9675.32,"z":-6048.0},"angles":{"x":0.0,"y":180.0,"z":0.0}},{"classname":"info_player_counterterrorist","origin":{"x":5325.59,"y":9615.85,"z":-6048.0},"angles":{"x":0.0,"y":180.0,"z":0.0}},{"classname":"info_player_counterterrorist","origin":{"x":5326.36,"y":9562.0,"z":-6048.0},"angles":{"x":0.0,"y":180.0,"z":0.0}},{"classname":"info_player_counterterrorist","origin":{"x":5326.97,"y":9475.81,"z":-6048.0},"angles":{"x":0.0,"y":180.0,"z":0.0}},{"classname":"info_player_counterterrorist","origin":{"x":5327.22,"y":9430.72,"z":-6048.0},"angles":{"x":0.0,"y":180.0,"z":0.0}},{"classname":"info_player_counterterrorist","origin":{"x":5327.59,"y":9386.22,"z":-6048.0},"angles":{"x":0.0,"y":180.0,"z":0.0}},{"classname":"info_player_counterterrorist","origin":{"x":5327.99,"y":9325.63,"z":-6048.0},"angles":{"x":0.0,"y":180.0,"z":0.0}},{"classname":"info_player_counterterrorist","origin":{"x":5333.34,"y":9260.87,"z":-6048.0},"angles":{"x":0.0,"y":180.0,"z":0.0}},{"classname":"trigger_teleport","origin":{"x":4704.0,"y":1104.0,"z":-7024.0}},{"classname":"trigger_teleport","origin":{"x":4704.0,"y":-1424.0,"z":-7024.0}},{"classname":"trigger_teleport","origin":{"x":10602.0,"y":-11072.0,"z":-15121.5}},{"classname":"trigger_teleport","origin":{"x":2912.0,"y":5696.0,"z":-1199.0}},{"model":67,"clusters":[839,842,845,871,874,876],"classname":"func_brush","origin":{"x":5920.0,"y":-160.0,"z":-7744.15}},{"model":68,"clusters":[837,840,843,865,870,872,875,880,883],"classname":"func_brush","origin":{"x":6384.0,"y":-160.0,"z":-8896.5}},{"model":69,"clusters":[344,418,425,489,500,598,600,651,652],"classname":"func_brush","origin":{"x":5288.0,"y":9920.0,"z":-8704.0}}]}